langmem0/__init__.py
langmem0/chat_model.py
langmem0/middleware.py
langmem0-0.1.0.dist-info/METADATA
langmem0-0.1.0.dist-info/WHEEL
langmem0-0.1.0.dist-info/top_level.txt
langmem0-0.1.0.dist-info/RECORD
