Metadata-Version: 2.4
Name: langmem0
Version: 0.1.0
Summary: Add your description here
Requires-Python: >=3.13
Requires-Dist: langchain<2,>=1
Requires-Dist: langchain-openai>=1.1.6
Requires-Dist: mem0ai>=1.0.1
Requires-Dist: pydantic>=2.12.5
